MANIFEST.in
README.rst
setup.py
flask_admin_openerp/__init__.py
flask_admin_openerp/filters.py
flask_admin_openerp/form.py
flask_admin_openerp.egg-info/PKG-INFO
flask_admin_openerp.egg-info/SOURCES.txt
flask_admin_openerp.egg-info/dependency_links.txt
flask_admin_openerp.egg-info/requires.txt
flask_admin_openerp.egg-info/top_level.txt
flask_admin_openerp/templates/admin_openerp/model/edit.html