Metadata-Version: 1.0
Name: flask-admin-openerp
Version: 0.3.3
Summary: OpenERP Backend for Flask-Admin
Home-page: http://www.gisce.net
Author: GISCE-TI, S.L.
Author-email: ti@gisce.net
License: MIT
Platform: UNKNOWN
